hulo/CHANGELOG.md
hulo/CODE_OF_CONDUCT.md
hulo/CONTRIBUTING.md
hulo/LICENSE
hulo/README.md
hulo/SECURITY.md
hulo/__init__.py
hulo/cli.py
hulo/hulo
hulo/__pycache__/__init__.cpython-311.pyc
hulo/__pycache__/cli.cpython-311.pyc
hulo/std/archive/archive.hl
hulo/std/archive/archive_test.hl
hulo/std/ast/expr.hl
hulo/std/ast/index.hl
hulo/std/ast/stmt.hl
hulo/std/builtin/bool.hl
hulo/std/builtin/bool_test.hl
hulo/std/builtin/constant.hl
hulo/std/builtin/index.hl
hulo/std/builtin/list.hl
hulo/std/builtin/list_test.hl
hulo/std/builtin/map.hl
hulo/std/builtin/map_test.hl
hulo/std/builtin/num.hl
hulo/std/builtin/num_test.hl
hulo/std/builtin/set.hl
hulo/std/builtin/set_test.hl
hulo/std/builtin/str.hl
hulo/std/builtin/str_test.hl
hulo/std/builtin/triple.hl
hulo/std/builtin/triple_test.hl
hulo/std/builtin/type.hl
hulo/std/builtin/type_posix.hl
hulo/std/builtin/type_test.hl
hulo/std/cfg/configure.hl
hulo/std/cfg/stream_configure.hl
hulo/std/cfg/json/index.hl
hulo/std/cfg/json/json_test.hl
hulo/std/cfg/toml/index.hl
hulo/std/cfg/toml/toml_test.hl
hulo/std/cfg/xml/index.hl
hulo/std/cfg/yaml/index.hl
hulo/std/cmd/a/a_win_test.hl
hulo/std/cmd/a/active.hl
hulo/std/cmd/a/add.hl
hulo/std/cmd/a/adprep.hl
hulo/std/cmd/a/aliax.hl
hulo/std/cmd/a/append.hl
hulo/std/cmd/a/arp.hl
hulo/std/cmd/a/assign.hl
hulo/std/cmd/a/assoc.hl
hulo/std/cmd/a/at.hl
hulo/std/cmd/a/atmadm.hl
hulo/std/cmd/a/awk.hl
hulo/std/cmd/b/bitsadmin.hl
hulo/std/cmd/c/cls.hl
hulo/std/cmd/c/color.hl
hulo/std/cmd/c/cd/cd_windows.hl
hulo/std/cmd/c/cd/index.hl
hulo/std/cmd/c/curl/curl.hl
hulo/std/cmd/c/curl/curl_posix.hl
hulo/std/cmd/d/del.hl
hulo/std/cmd/d/docwiz.hl
hulo/std/cmd/e/echo/echo.hl
hulo/std/cmd/e/echo/echo_bash.hl
hulo/std/cmd/e/echo/echo_batch.hl
hulo/std/cmd/e/echo/echo_ps.hl
hulo/std/cmd/e/exit/exit_win.hl
hulo/std/cmd/f/findstr.hl
hulo/std/cmd/g/gawk.hl
hulo/std/cmd/g/grep.hl
hulo/std/cmd/i/iptables.hl
hulo/std/cmd/n/netsh.hl
hulo/std/cmd/p/pause.hl
hulo/std/cmd/p/ping.hl
hulo/std/cmd/s/setlocal.hl
hulo-0.1.1.dist-info/licenses/LICENSE
hulo-0.1.1.dist-info/METADATA
hulo-0.1.1.dist-info/WHEEL
hulo-0.1.1.dist-info/entry_points.txt
hulo-0.1.1.dist-info/top_level.txt
hulo-0.1.1.dist-info/RECORD
