Metadata-Version: 2.4
Name: hulo
Version: 0.1.1
Summary: Hulo programming language compiler and runtime
Home-page: https://github.com/hulo-lang/hulo
Author: The Hulo Authors
Author-email: 
Requires-Python: >=3.7
License-File: LICENSE
Dynamic: author
Dynamic: description
Dynamic: description-content-type
Dynamic: home-page
Dynamic: license-file
Dynamic: requires-python
Dynamic: summary
